{
  "Questions": [
    {
      "AnswerRequired": true,
      "QuestionTask": "Bitte ordnen sie die Proben in ihrer geschmacklichen Intensit채t.\nDie neutralste Probe ist links (Nr. 1), die intensiveste Probe rechts (Nr. 6).\nDr체cken sie auf <WEITER> und f체hren Sie danach die Studie durch.",
      "QuestionType": "2",
      "QuestionElements": [
        {
          "IndexNumber": 0,
          "TextMessage": "Verstanden.",
          "IsSelected": true,
          "HasTextInput": false
        }
      ]
    },
    {
      "AnswerRequired": true,
      "QuestionTask": "Studie durchgef체hrt.",
      "QuestionType": "2",
      "QuestionElements": [
        {
        }
      ]
    }
  ]
}